api/__init__.py
api/orchestrator.py
api/provisioner.py
command/__init__.py
command/ozwald.py
config/reader.py
context/__init__.py
context/builder/__init__.py
context/builder/interfaces.py
context/library/__init__.py
context/library/analyze.py
hosts/__init__.py
hosts/resources.py
orchestration/__init__.py
orchestration/models.py
orchestration/provisioner.py
orchestration/service.py
services/__init__.py
services/container.py
services/testing.py
util/__init__.py
util/active_services_cache.py
util/cache_queue.py
util/cli.py
util/http.py
util/logger.py
util/profiler_request_cache.py
util/services.py
ozwald-0.0.1.dist-info/METADATA
ozwald-0.0.1.dist-info/WHEEL
ozwald-0.0.1.dist-info/entry_points.txt
ozwald-0.0.1.dist-info/top_level.txt
ozwald-0.0.1.dist-info/RECORD
