Metadata-Version: 2.4
Name: ozwald
Version: 0.0.1
Summary: Ozwald is a multi-tool for container provisioning.
Author-email: Fred McDavid <fred@frameworklabs.us>
License: MIT
Project-URL: Homepage, https://github.com/FredworkLemmas/ozwald.git
Project-URL: Repository, https://github.com/FredworkLemmas/ozwald.git
Project-URL: Bug Tracker, https://github.com/FredworkLemmas/ozwald.git/issues
Keywords: ozwald,LLM,assistant,orchestration,composition
Classifier: Development Status :: 2 - Pre-Alpha
Classifier: Intended Audience :: Developers
Classifier: License :: OSI Approved :: MIT License
Classifier: Operating System :: OS Independent
Classifier: Programming Language :: Python :: 3
Classifier: Programming Language :: Python :: 3.8
Classifier: Programming Language :: Python :: 3.9
Classifier: Programming Language :: Python :: 3.10
Classifier: Programming Language :: Python :: 3.11
Classifier: Programming Language :: Python :: 3.12
Classifier: Topic :: Software Development :: Libraries :: Python Modules
Classifier: Topic :: System :: Systems Administration
Requires-Python: >=3.8
Requires-Dist: invocate>=0.2.1
Requires-Dist: attrs>=21.0.0
Requires-Dist: requests>=2.32.5
Requires-Dist: PyYAML>=6.0.1
Requires-Dist: psutil>=7.1.3
Requires-Dist: pydantic>=2.12.5
Requires-Dist: nvidia-ml-py>=13.580.82
Requires-Dist: amdsmi>=6.4.4
Requires-Dist: python-dotenv>=1.2.1
Requires-Dist: fastapi>=0.121.0
Requires-Dist: redis>=7.0.1
Provides-Extra: api
Requires-Dist: uvicorn[standard]; extra == "api"
Provides-Extra: dev
Requires-Dist: pytest>=7.0; extra == "dev"
Requires-Dist: pytest-cov; extra == "dev"
Requires-Dist: pytest-mock; extra == "dev"
Requires-Dist: pytest-docker-tools; extra == "dev"
Requires-Dist: mkdocs; extra == "dev"
Requires-Dist: coverage; extra == "dev"
Requires-Dist: pre-commit; extra == "dev"
Requires-Dist: ruff; extra == "dev"
Requires-Dist: mypy; extra == "dev"
Requires-Dist: bandit[toml]; extra == "dev"
Requires-Dist: codespell; extra == "dev"
Requires-Dist: tox; extra == "dev"
Requires-Dist: uv; extra == "dev"
Requires-Dist: httpx; extra == "dev"
Provides-Extra: docs
